xcy_MVtest/__init__.py
xcy_MVtest/__version__.py
xcy_MVtest/core.py
xcy_MVtest-1.0.0.dist-info/DESCRIPTION.rst
xcy_MVtest-1.0.0.dist-info/METADATA
xcy_MVtest-1.0.0.dist-info/RECORD
xcy_MVtest-1.0.0.dist-info/WHEEL
xcy_MVtest-1.0.0.dist-info/metadata.json
xcy_MVtest-1.0.0.dist-info/top_level.txt
